cp_common/__init__.py
cp_common/base.py
cp_common/log.py
cp_common/process.py
cp_common/req.py
cp_common/utils.py
cp_common-0.1.9.1.dist-info/WHEEL
cp_common-0.1.9.1.dist-info/METADATA
cp_common-0.1.9.1.dist-info/RECORD
