Metadata-Version: 2.1
Name: cp-common
Version: 0.1.9.1
Summary: 
Author: zmf963
Author-email: zmf96@qq.com
Requires-Python: >=3.8,<4.0
Classifier: Programming Language :: Python :: 3
Classifier: Programming Language :: Python :: 3.10
Classifier: Programming Language :: Python :: 3.8
Classifier: Programming Language :: Python :: 3.9
Requires-Dist: loguru (>=0.6.0,<0.7.0)
Requires-Dist: requests (>=2.0.1,<3.0.0)
Requires-Dist: rich (>=12.4.4,<13.0.0)
